LICENSE
README.md
setup.py
cvnets/__init__.py
cvnets/__version__.py
cvnets.egg-info/PKG-INFO
cvnets.egg-info/SOURCES.txt
cvnets.egg-info/dependency_links.txt
cvnets.egg-info/requires.txt
cvnets.egg-info/top_level.txt
cvnets/configs/__init__.py
cvnets/configs/parser.py
cvnets/configs/base/garbage_classification.yaml
cvnets/configs/base/sample_efficientnet_b0.yaml
cvnets/configs/base/sample_mobilevit_s.yaml
cvnets/configs/base/sample_nn.yaml
cvnets/configs/data/fashionmnist.yaml
cvnets/configs/data/garbage.yaml
cvnets/configs/model/efficientnet_b0.yaml
cvnets/configs/model/mobilevit_s.yaml
cvnets/configs/model/nn.yaml
cvnets/data/__init__.py
cvnets/data/loader.py
cvnets/losses/__init__.py
cvnets/losses/loss.py
cvnets/models/__init__.py
cvnets/models/factory.py
cvnets/optims/__init__.py
cvnets/optims/optimizer.py
cvnets/run/__init__.py
cvnets/run/moderator.py
cvnets/utils/__init__.py
cvnets/utils/cam.py
cvnets/utils/checkpoint.py
cvnets/utils/util.py