Metadata-Version: 2.1
Name: cvnets
Version: 0.2.5
Summary: Library for Computer Vision Deep Learning Networks
Author: Jihoon Lucas Kim
License-File: LICENSE
